{
  "description": "Manual prefix configurations for the production environment",
  "prefixes": [
    {
      "vrf_id": "prod-vrf",
      "cidr": "10.0.0.0/8",
      "parent_prefix_id": null,
      "tags": {
        "env": "prod",
        "managed_by": "engineer"
      },
      "routable": true,
      "vpc_children_type_flag": false,
      "description": "Root prefix for production environment"
    },
    {
      "vrf_id": "prod-vrf", 
      "cidr": "10.0.0.0/12",
      "parent_prefix_id": "manual-prod-vrf-10-0-0-0-8",
      "tags": {
        "env": "prod",
        "purpose": "prod_reservation"
      },
      "routable": true,
      "vpc_children_type_flag": false,
      "description": "Production environment reservation within 10.0.0.0/8"
    },
    {
      "vrf_id": "prod-vrf",
      "cidr": "10.0.0.0/16", 
      "parent_prefix_id": "manual-prod-vrf-10-0-0-0-12",
      "tags": {
        "purpose": "vpc_reservation",
        "description": "Reserved for production VPC"
      },
      "routable": true,
      "vpc_children_type_flag": true,
      "description": "VPC reservation for routable production services"
    },
    {
      "vrf_id": "prod-vrf",
      "cidr": "10.1.0.0/16",
      "parent_prefix_id": "manual-prod-vrf-10-0-0-0-12", 
      "tags": {
        "purpose": "vpc_reservation",
        "description": "Reserved for development/test VPC"
      },
      "routable": false,
      "vpc_children_type_flag": true,
      "description": "VPC reservation for non-routable development services"
    }
  ]
}
